just_ship_it.py
just_ship_it-0.0.6.dist-info/METADATA
just_ship_it-0.0.6.dist-info/RECORD
just_ship_it-0.0.6.dist-info/WHEEL
just_ship_it-0.0.6.dist-info/top_level.txt
