Metadata-Version: 2.1
Name: just-ship-it
Version: 0.0.6
Summary: For when you just need to ship your Python code.
Home-page: https://github.com/gstaff/just-ship-it
Author: Grant Stafford
License: UNKNOWN
Keywords: demo
Platform: UNKNOWN
Classifier: Programming Language :: Python :: 3.6
Classifier: License :: OSI Approved :: Apache Software License
Classifier: Operating System :: OS Independent
Requires-Dist: flask-ngrok
Requires-Dist: flask-restplus
